{
  "course_title": "Civilsetmilitaires1GM",
  "original_sections": 19,
  "adapted_sections": [
    {
      "original_title": "INTRODUCTION AU CHAPITRE 1",
      "adapted_title": "INTRODUCTION AU CHAPITRE 1",
      "original_content_preview": "Histoire des arts : la guerre d’Otto Dix (1929-1932)\nOtto Dix (1891-1969) est un peintre allemand qui participe à la Première Guerre mondiale.\nIl\ndénonce\nensuite les atrocités\ndes\ncombats dans\nplusieu...",
      "adapted_content": "TEXTE ADAPTÉ POUR DYSLEXIQUES :\n\n---\n\n**Titre : Otto Dix et la Guerre**\n\n**1. Qui est Otto Dix ?**\n- Otto Dix est un peintre allemand.\n- Il est né en 1891 et mort en 1969.\n- Il a vécu la Première Guerre mondiale.\n\n**2. Ses Œuvres Principales :**\n- **La Tranchée (1918) :** Montre l'horreur des tranchées pendant la guerre.\n- **Les Joueurs de skat (1920) :** Des soldats blessés jouent aux cartes.\n- **La Guerre (1929-1932) :** Représente les destructions causées par la guerre.\n\n**3. L'Art Dégénéré :**\n- Les nazis considèrent l'art de Dix comme \"dégénéré\".\n- Plusieurs de ses œuvres sont détruites après 1933.\n\n**Activité : Raconter une Histoire**\n- Choisis une œuvre d'Otto Dix.\n- Imagine une courte histoire basée sur cette œuvre.\n- Numérote les étapes de ton histoire.\n\n**Exemple :**\n1. Un soldat se cache dans une tranchée.\n2. Il entend des bruits de bombes.\n3. Il pense à sa famille.\n\n---\n\nUtilise ces informations pour mieux comprendre l'art d'Otto Dix et l'impact de la guerre sur ses œuvres.",
      "sources": [
        {
          "source": "LeMans_GASNIER_Amandine_EPD_2019.pdf",
          "author": "Amandine Gasnier",
          "section": "Content",
          "page": 45.0,
          "relevance_score": 0.517807841
        },
        {
          "source": "LeMans_GASNIER_Amandine_EPD_2019.pdf",
          "author": "Amandine Gasnier",
          "section": "Sommaire",
          "page": 7.0,
          "relevance_score": 0.516245782
        },
        {
          "source": "DIAS_Juliette_PE25_2020.pdf",
          "author": "Juliette Dias",
          "section": "SOMMAIRE",
          "page": 4.0,
          "relevance_score": 0.513073921
        },
        {
          "source": "LeMans_GASNIER_Amandine_EPD_2019.pdf",
          "author": "Amandine Gasnier",
          "section": "Famille",
          "page": 26.0,
          "relevance_score": 0.507283449
        },
        {
          "source": "MEMOIRE Meynaert Emilie 2022-2023.pdf",
          "author": "Meynaert, E.",
          "section": "Content",
          "page": 3.0,
          "relevance_score": 0.505203068
        }
      ],
      "page": 2
    },
    {
      "original_title": "TRAVAIL PERSONNEL OU EN GROUPE:",
      "adapted_title": "TRAVAIL PERSONNEL OU EN GROUPE:",
      "original_content_preview": "Rédigez un petit texte de quelques lignes qui vous permettra de présenter ce\ntableau à l’oral.\n\n-\nPrésentez le tableau et son auteur\n-\nDécrivez-le\n-\nInterprétez-le\n-\nDonnez votre avis sur cette œuvre...",
      "adapted_content": "TITRE ADAPTÉ : TRAVAIL PERSONNEL OU EN GROUPE : PRÉSENTATION D'UN TABLEAU\n\n1. **Présentation du Tableau et de l'Auteur**\n\n   - Choisis un tableau que tu aimes.\n   - Écris le nom du tableau.\n   - Écris le nom de l'artiste.\n\n   *Exemple : \"La Joconde\" par Léonard de Vinci.*\n\n2. **Description du Tableau**\n\n   - Regarde bien le tableau.\n   - Note les détails importants.\n   - Décris les couleurs et les formes.\n\n   *Exemple : \"La Joconde a un fond sombre, et Mona Lisa sourit légèrement.\"*\n\n3. **Interprétation du Tableau**\n\n   - Que ressens-tu en regardant le tableau ?\n   - Que penses-tu que le tableau veut dire ?\n\n   *Exemple : \"Je pense que Mona Lisa semble mystérieuse et calme.\"*\n\n4. **Ton Avis sur l'Œuvre**\n\n   - Aimes-tu ce tableau ? Pourquoi ?\n   - Écris ce que tu penses de l'œuvre.\n\n   *Exemple : \"J'aime ce tableau parce qu'il est beau et célèbre.\"*\n\nStructure tes idées avec ces étapes. Utilise des phrases simples et claires.",
      "sources": [
        {
          "source": "LeMans_GASNIER_Amandine_EPD_2019.pdf",
          "author": "Amandine Gasnier",
          "section": "Introduction",
          "page": 8.0,
          "relevance_score": 0.44712308
        },
        {
          "source": "LeMans_GASNIER_Amandine_EPD_2019.pdf",
          "author": "Amandine Gasnier",
          "section": "Ecrit",
          "page": 25.0,
          "relevance_score": 0.446416795
        },
        {
          "source": "LeMans_GASNIER_Amandine_EPD_2019.pdf",
          "author": "Amandine Gasnier",
          "section": "Famille",
          "page": 26.0,
          "relevance_score": 0.440591186
        },
        {
          "source": "LeMans_GASNIER_Amandine_EPD_2019.pdf",
          "author": "Amandine Gasnier",
          "section": "Sommaire",
          "page": 7.0,
          "relevance_score": 0.439143836
        },
        {
          "source": "DIAS_Juliette_PE25_2020.pdf",
          "author": "Juliette Dias",
          "section": "INTRODUCTION GENERALE",
          "page": 5.0,
          "relevance_score": 0.433994085
        }
      ],
      "page": 3
    },
    {
      "original_title": "ACTIVITÉ 1 : LA PREMIÈRE GUERRE MONDIALE",
      "adapted_title": "ACTIVITÉ 1 : LA PREMIÈRE GUERRE MONDIALE",
      "original_content_preview": "Question : Qu’est-ce que la première guerre mondiale ?\nCompétences attendues : avoir des repères\nSupports : Livre et vidéo INA...",
      "adapted_content": "TEXTE ADAPTÉ POUR DYSLEXIQUES :\n\nActivité 1 : La Première Guerre Mondiale\n\n**Compétences attendues**\n- Avoir des repères historiques simples\n\n**Supports**\n- Livre d'histoire\n- Vidéo INA (Institut National de l'Audiovisuel)\n\n**Question : Qu'est-ce que la Première Guerre Mondiale ?**\n\n1. **Définition**\n   - La Première Guerre Mondiale a eu lieu de 1914 à 1918.\n   - Elle a impliqué de nombreux pays dans le monde.\n\n2. **Les Causes**\n   - Tensions entre pays européens.\n   - Assassinat de l'archiduc François-Ferdinand.\n\n3. **Les Principaux Pays Impliqués**\n   - France\n   - Royaume-Uni\n   - Allemagne\n   - Russie\n   - États-Unis (à partir de 1917)\n\n4. **Conséquences**\n   - Millions de morts et blessés.\n   - Changements de frontières en Europe.\n\n**Exemples concrets :**\n- Utilise le livre pour voir des cartes de l'Europe avant et après la guerre.\n- Regarde la vidéo pour comprendre le quotidien des soldats.\n\n**Points clés à retenir**\n- La guerre a duré 4 ans.\n- Elle a bouleversé le monde entier.\n- Comprendre les causes aide à éviter de futurs conflits.\n\n**Activité :**\n- Dessine une carte simple de l'Europe montrant les pays impliqués.\n- Écris une phrase sur ce que tu as appris en regardant la vidéo.",
      "sources": [
        {
          "source": "LeMans_GASNIER_Amandine_EPD_2019.pdf",
          "author": "Amandine Gasnier",
          "section": "Famille",
          "page": 26.0,
          "relevance_score": 0.513494968
        },
        {
          "source": "LeMans_GASNIER_Amandine_EPD_2019.pdf",
          "author": "Amandine Gasnier",
          "section": "Sommaire",
          "page": 7.0,
          "relevance_score": 0.506073654
        },
        {
          "source": "LeMans_GASNIER_Amandine_EPD_2019.pdf",
          "author": "Amandine Gasnier",
          "section": "Content",
          "page": 14.0,
          "relevance_score": 0.503476501
        },
        {
          "source": "MEMOIRE Meynaert Emilie 2022-2023.pdf",
          "author": "Meynaert, E.",
          "section": "Content",
          "page": 3.0,
          "relevance_score": 0.50009352
        },
        {
          "source": "DIAS_Juliette_PE25_2020.pdf",
          "author": "Juliette Dias",
          "section": "SOMMAIRE",
          "page": 4.0,
          "relevance_score": 0.499913126
        }
      ],
      "page": 3
    }
  ],
  "general_adaptations": {
    "adapted_introduction": "### Introduction au Cours : Les Civils et les Militaires pendant la Première Guerre Mondiale\n\n#### La Première Guerre Mondiale\n\n1. **Début du Conflit :**\n   - La guerre a commencé en 1914.\n   - Elle a impliqué de nombreux pays du monde entier.\n\n2. **Les Deux Camps :**\n   - **Triple Entente :** France, Royaume-Uni, Russie.\n   - **Triple Alliance :** Allemagne, Autriche-Hongrie, Italie.\n\n#### Les Civils pendant la Guerre\n\n1. **Vie Quotidienne :**\n   - Les civils ont souffert de la pénurie de nourriture.\n   - Beaucoup ont travaillé dans les usines pour fabriquer des armes.\n\n2. **Rôle Important :**\n   - Les femmes ont remplacé les hommes partis au front dans les usines et les fermes.\n\n#### Les Militaires pendant la Guerre\n\n1. **La Vie dans les Tranchées :**\n   - Les soldats vivaient dans des tranchées boueuses.\n   - Ils faisaient face à des conditions difficiles : froid, faim, et maladies.\n\n2. **Les Batailles :**\n   - Des batailles célèbres incluent la Bataille de la Somme et Verdun.\n\n#### Exemples et Illustrations\n\n- **Exemple de Civil :** Marie, une femme travaillant dans une usine de munitions.\n- **Exemple de Militaire :** Pierre, un soldat français dans les tranchées de Verdun.\n\n---\n\nCe texte utilise un langage simple et des phrases courtes pour aider à la compréhension. Il est structuré avec des titres clairs pour séparer les idées principales. Des exemples concrets sont fournis pour rendre le contenu plus accessible.",
    "sources": [
      {
        "source": "LeMans_GASNIER_Amandine_EPD_2019.pdf",
        "author": "Amandine Gasnier",
        "section": "Famille",
        "page": 26.0,
        "relevance_score": 0.543406785
      },
      {
        "source": "LeMans_GASNIER_Amandine_EPD_2019.pdf",
        "author": "Amandine Gasnier",
        "section": "Introduction",
        "page": 8.0,
        "relevance_score": 0.543046951
      },
      {
        "source": "LeMans_GASNIER_Amandine_EPD_2019.pdf",
        "author": "Amandine Gasnier",
        "section": "Content",
        "page": 17.0,
        "relevance_score": 0.53772223
      },
      {
        "source": "LeMans_GASNIER_Amandine_EPD_2019.pdf",
        "author": "Amandine Gasnier",
        "section": "Content",
        "page": 35.0,
        "relevance_score": 0.536610425
      },
      {
        "source": "MEMOIRE Meynaert Emilie 2022-2023.pdf",
        "author": "Meynaert, E.",
        "section": "Content",
        "page": 23.0,
        "relevance_score": 0.532924533
      }
    ]
  },
  "exercise_adaptations": [
    {
      "original_exercise": "TRAVAIL PERSONNEL OU EN GROUPE:",
      "adapted_exercise": "EXERCICE ADAPTÉ POUR ÉLÈVES DYSLEXIQUES :\n\n**CHAPITRE : Comprendre les identités multiples**\n\n**Objectif :** Identifier les composantes de son identité\n\n**Activité : Découvrir les identités multiples**\n\n**Étapes à suivre :**\n\n1. **Lire le texte sur les identités multiples**\n   - Utilise une police claire comme OpenDyslexic.\n   - Taille de la police : 14.\n   - Espacement : 2 entre les lignes.\n\n2. **Définir l'identité**\n   - En deux phrases simples, écris ce qu'est l'identité d'une personne.\n   - Exemple : \"Mon identité, c'est ce qui me rend unique. C'est mon nom, ma culture, et mes goûts.\"\n\n3. **Liste des composantes de ton identité**\n   - Écris trois choses qui te définissent.\n   - Exemple : \"Je suis un frère, un passionné de football, et j'aime le chocolat.\"\n\n4. **Travailler en groupe**\n   - Discuter avec deux amis.\n   - Chacun partage une composante de son identité.\n\n5. **Illustrer son identité**\n   - Dessine un symbole pour chaque composante de ton identité.\n   - Exemple : Un ballon pour le foot, un cœur pour la famille.\n\n**Aide visuelle :**\n\n- Utilise des images pour illustrer les concepts.\n- Inclure des icônes pour chaque étape (livre pour la lecture, stylo pour l'écriture, personnes pour le groupe).\n\n**Rappel :** L'identité, c'est ce qui fait que tu es toi, avec tes qualités et tes intérêts.\n\nCe format permet d'assurer que les élèves dyslexiques suivent facilement les consignes grâce à une structure claire et visuelle.",
      "sources": [
        {
          "source": "LeMans_GASNIER_Amandine_EPD_2019.pdf",
          "author": "Amandine Gasnier",
          "section": "Content",
          "page": 18.0,
          "relevance_score": 0.552675903
        },
        {
          "source": "LeMans_GASNIER_Amandine_EPD_2019.pdf",
          "author": "Amandine Gasnier",
          "section": "Content",
          "page": 22.0,
          "relevance_score": 0.548700869
        },
        {
          "source": "LeMans_GASNIER_Amandine_EPD_2019.pdf",
          "author": "Amandine Gasnier",
          "section": "Famille",
          "page": 26.0,
          "relevance_score": 0.54842329
        },
        {
          "source": "LeMans_GASNIER_Amandine_EPD_2019.pdf",
          "author": "Amandine Gasnier",
          "section": "Content",
          "page": 35.0,
          "relevance_score": 0.547120333
        },
        {
          "source": "MEMOIRE Meynaert Emilie 2022-2023.pdf",
          "author": "Meynaert, E.",
          "section": "Content",
          "page": 3.0,
          "relevance_score": 0.544771433
        }
      ]
    },
    {
      "original_exercise": "ACTIVITÉ 1 : LA PREMIÈRE GUERRE MONDIALE",
      "adapted_exercise": "EXERCICE ADAPTÉ : ACTIVITÉ 1 : LA PREMIÈRE GUERRE MONDIALE\n\n**Titre : La Première Guerre Mondiale**\n\n**Objectif :** Comprendre les événements clés de la Première Guerre Mondiale\n\n**Instructions :**\n\n1. **Lire les informations suivantes :**\n\n   - La Première Guerre Mondiale a commencé en 1914 et s'est terminée en 1918.\n   - Elle a opposé deux grandes alliances : la Triple Entente (France, Royaume-Uni, Russie) et les Puissances Centrales (Allemagne, Autriche-Hongrie, Empire Ottoman).\n\n2. **Questions à Choix Multiples :**\n\n   a. Quand la Première Guerre Mondiale a-t-elle commencé ?\n   \n   - [ ] 1912\n   - [X] 1914\n   - [ ] 1916\n\n   b. Quel pays ne faisait pas partie de la Triple Entente ?\n   \n   - [ ] France\n   - [ ] Royaume-Uni\n   - [X] Allemagne\n\n3. **Vocabulaire Simple :**\n\n   - **Entente :** Accord ou alliance entre pays.\n   - **Alliance :** Groupe de pays qui s'unissent pour un but commun.\n\n4. **Activité Visuelle :**\n\n   - Dessine deux cercles sur une feuille.\n   - Dans le premier cercle, écris les pays de la Triple Entente.\n   - Dans le second cercle, écris les pays des Puissances Centrales.\n\n5. **Réflexion :**\n\n   - Pourquoi pensez-vous que les pays ont formé des alliances ?\n\n**Aide Supplémentaire :**\n\n- Utilisez des cartes colorées pour montrer les alliances.\n- Lisez les informations à voix haute avec un partenaire.\n\n**Source :** Adapté à partir des informations sur la dyslexie et comment structurer les cours pour les élèves dyslexiques (Gasnier, 2019 ; Meynaert, 2022).",
      "sources": [
        {
          "source": "LeMans_GASNIER_Amandine_EPD_2019.pdf",
          "author": "Amandine Gasnier",
          "section": "Famille",
          "page": 26.0,
          "relevance_score": 0.51469034
        },
        {
          "source": "LeMans_GASNIER_Amandine_EPD_2019.pdf",
          "author": "Amandine Gasnier",
          "section": "Content",
          "page": 17.0,
          "relevance_score": 0.500124156
        },
        {
          "source": "MEMOIRE Meynaert Emilie 2022-2023.pdf",
          "author": "Meynaert, E.",
          "section": "Content",
          "page": 3.0,
          "relevance_score": 0.498497874
        },
        {
          "source": "LeMans_GASNIER_Amandine_EPD_2019.pdf",
          "author": "Amandine Gasnier",
          "section": "Sommaire",
          "page": 7.0,
          "relevance_score": 0.497546345
        },
        {
          "source": "MEMOIRE Meynaert Emilie 2022-2023.pdf",
          "author": "Meynaert, E.",
          "section": "Content",
          "page": 23.0,
          "relevance_score": 0.496042788
        }
      ]
    },
    {
      "original_exercise": "Question : Qu’est-ce que la première guerre mondiale ?",
      "adapted_exercise": "EXERCICE ADAPTÉ : \n\n**Titre : Comprendre la Première Guerre Mondiale**\n\n**Question : Qu'est-ce que la Première Guerre Mondiale ?**\n\n**Consignes :**\n\n1. **Lire le texte simplifié :**\n   - La Première Guerre Mondiale a eu lieu de 1914 à 1918.\n   - Elle a commencé en Europe.\n   - Beaucoup de pays étaient impliqués.\n   - Elle a causé beaucoup de destructions.\n\n2. **Répondre aux questions :**\n   - Quand a eu lieu la Première Guerre Mondiale ? \n   - Où a-t-elle commencé ?\n   - Combien de pays étaient impliqués ? (Choisir parmi : quelques pays, beaucoup de pays)\n   - Qu'est-ce que la guerre a causé ? (Choisir parmi : peu de destructions, beaucoup de destructions)\n\n**Instructions étape par étape :**\n\n1. **Étape 1 : Lecture**\n   - Lis attentivement chaque phrase du texte simplifié.\n   - Utilise tes doigts pour suivre les lignes si tu en as besoin.\n\n2. **Étape 2 : Répondre aux questions**\n   - Relis la question.\n   - Trouve la réponse dans le texte.\n   - Choisis la bonne réponse parmi les options données.\n\n**Aide visuelle :**\n\n- Utilise une carte simple de l'Europe montrant les pays impliqués.\n- Dessine une chronologie simple avec les années 1914 à 1918.\n\n**Exemple visuel :**\n\n- Une image montrant des soldats de l'époque.\n- Une photo de la carte de l'Europe durant la guerre.\n\n**Note :** Utilise un texte en police \"Opendyslexic\" et taille 14 pour faciliter la lecture. \n\nCette adaptation vise à rendre l'exercice accessible en réduisant la charge cognitive et en fournissant des supports visuels et structurés.",
      "sources": [
        {
          "source": "LeMans_GASNIER_Amandine_EPD_2019.pdf",
          "author": "Amandine Gasnier",
          "section": "Famille",
          "page": 26.0,
          "relevance_score": 0.504935741
        },
        {
          "source": "DIAS_Juliette_PE25_2020.pdf",
          "author": "Juliette Dias",
          "section": "SOMMAIRE",
          "page": 4.0,
          "relevance_score": 0.499316692
        },
        {
          "source": "MEMOIRE Meynaert Emilie 2022-2023.pdf",
          "author": "Meynaert, E.",
          "section": "Content",
          "page": 39.0,
          "relevance_score": 0.498919904
        },
        {
          "source": "LeMans_GASNIER_Amandine_EPD_2019.pdf",
          "author": "Amandine Gasnier",
          "section": "Content",
          "page": 22.0,
          "relevance_score": 0.497350097
        },
        {
          "source": "LeMans_GASNIER_Amandine_EPD_2019.pdf",
          "author": "Amandine Gasnier",
          "section": "Content",
          "page": 67.0,
          "relevance_score": 0.496679366
        }
      ]
    }
  ],
  "instruction_adaptations": [
    {
      "original_instruction": "Lisez ce tableau comme une histoire. Numérotez-le et racontez-moi ce que vous",
      "adapted_instruction": "CONSIGNE ADAPTÉE :\n\nLis le tableau comme une histoire.\n1. Numérote les informations du tableau.\n2. Raconte cette histoire avec tes mots.\n\nStructure claire, étapes simples et précises pour faciliter la compréhension des élèves dyslexiques.",
      "sources": [
        {
          "source": "LeMans_GASNIER_Amandine_EPD_2019.pdf",
          "author": "Amandine Gasnier",
          "section": "Famille",
          "page": 26.0,
          "relevance_score": 0.552609563
        },
        {
          "source": "LeMans_GASNIER_Amandine_EPD_2019.pdf",
          "author": "Amandine Gasnier",
          "section": "Sommaire",
          "page": 7.0,
          "relevance_score": 0.534579337
        },
        {
          "source": "MEMOIRE Meynaert Emilie 2022-2023.pdf",
          "author": "Meynaert, E.",
          "section": "Content",
          "page": 3.0,
          "relevance_score": 0.52844435
        },
        {
          "source": "DIAS_Juliette_PE25_2020.pdf",
          "author": "Juliette Dias",
          "section": "SOMMAIRE",
          "page": 4.0,
          "relevance_score": 0.528043449
        },
        {
          "source": "LeMans_GASNIER_Amandine_EPD_2019.pdf",
          "author": "Amandine Gasnier",
          "section": "Content",
          "page": 35.0,
          "relevance_score": 0.51865375
        }
      ]
    },
    {
      "original_instruction": "Décrivez le paysage, par quoi est-il détruit ? Quelles conséquences cela a-t-il sur les",
      "adapted_instruction": "CONSIGNE ADAPTÉE :\n\nDécrivez le paysage.\n\n1. Observez ce qui détruit le paysage.\n2. Expliquez les conséquences de cette destruction.\n\n- Utilisez des phrases simples.\n- Donnez des exemples concrets.\n- Suivez l'ordre indiqué.",
      "sources": [
        {
          "source": "LeMans_GASNIER_Amandine_EPD_2019.pdf",
          "author": "Amandine Gasnier",
          "section": "Sommaire",
          "page": 7.0,
          "relevance_score": 0.518497646
        },
        {
          "source": "DIAS_Juliette_PE25_2020.pdf",
          "author": "Juliette Dias",
          "section": "SOMMAIRE",
          "page": 4.0,
          "relevance_score": 0.50903368
        },
        {
          "source": "LeMans_GASNIER_Amandine_EPD_2019.pdf",
          "author": "Amandine Gasnier",
          "section": "Famille",
          "page": 26.0,
          "relevance_score": 0.505386651
        },
        {
          "source": "MEMOIRE Meynaert Emilie 2022-2023.pdf",
          "author": "Meynaert, E.",
          "section": "Content",
          "page": 3.0,
          "relevance_score": 0.494375825
        },
        {
          "source": "DIAS_Juliette_PE25_2020.pdf",
          "author": "Juliette Dias",
          "section": "Content",
          "page": 59.0,
          "relevance_score": 0.493184984
        }
      ]
    },
    {
      "original_instruction": "Quelle impression générale se dégage du tableau ? Expliquez comment le peintre a",
      "adapted_instruction": "CONSIGNE ORIGINALE: Quelle impression générale se dégage du tableau ? Expliquez comment le peintre a\n\nCONSIGNE ADAPTÉE :\n\n1. Regarde le tableau attentivement.\n2. Imagine ce que tu ressens en le regardant.\n3. Note en quelques mots ton impression générale.\n4. Regarde les couleurs et les formes utilisées par le peintre.\n5. Écris comment ces éléments te font ressentir cette impression.\n6. Prends ton temps pour bien observer chaque détail. \n\nCes consignes utilisent des phrases courtes et simples, avec un ordre logique pour aider à la compréhension.",
      "sources": [
        {
          "source": "formation3-1 AESH - copie.pdf",
          "author": "Unknown Author",
          "section": "Content",
          "page": 30.0,
          "relevance_score": 0.496530592
        },
        {
          "source": "MEMOIRE Meynaert Emilie 2022-2023.pdf",
          "author": "Meynaert, E.",
          "section": "Content",
          "page": 39.0,
          "relevance_score": 0.481214106
        },
        {
          "source": "LeMans_GASNIER_Amandine_EPD_2019.pdf",
          "author": "Amandine Gasnier",
          "section": "Famille",
          "page": 26.0,
          "relevance_score": 0.480319768
        },
        {
          "source": "MEMOIRE Meynaert Emilie 2022-2023.pdf",
          "author": "Meynaert, E.",
          "section": "Content",
          "page": 37.0,
          "relevance_score": 0.477637947
        },
        {
          "source": "Guide-Dyslexie-FranceDyslexia.pdf",
          "author": "Unknown Author",
          "section": "Content",
          "page": 15.0,
          "relevance_score": 0.474455893
        }
      ]
    }
  ],
  "formatting_recommendations": {
    "guide": "Guide de Mise en Forme : Cours 'Civilsetmilitaires1GM' Adapté aux Dyslexiques\n\n**1. Choix des Caractères et Mise en Page**\n\n- **Police de Caractères** : Utilisez la police \"Open Dyslexic\". Elle est spécialement conçue pour les lecteurs dyslexiques.\n- **Taille du Texte** : Utilisez une taille de police de 12 à 14 points pour une meilleure lisibilité.\n- **Espacement** : Augmentez l'espacement entre les lignes (1,5 interligne) et les mots pour faciliter la lecture.\n- **Format des Pages** : Numérotez clairement chaque page et évitez les impressions recto-verso pour simplifier la navigation dans le document.\n\n**2. Structuration du Contenu**\n\n- **Titres et Sous-titres** : Utilisez des titres en gras et de couleurs différentes pour chaque section. Par exemple, \"Introduction\", \"Les Causes de la Guerre\", etc.\n- **Listes à Puces** : Présentez les informations sous forme de listes à puces pour les rendre plus digestes.\n- **Textes Courts** : Divisez le texte en petits paragraphes avec des phrases courtes et simples.\n\n**3. Supports Visuels**\n\n- **Schémas et Images** : Intégrez des images et des schémas explicatifs. Par exemple, une carte des alliances pendant la Première Guerre mondiale.\n- **Couleurs** : Utilisez l'outil \"Lire couleur\" pour marquer les syllabes et phonèmes. Par exemple, alternez les couleurs pour chaque syllabe dans un mot important.\n\n**4. Consignes et Exercices**\n\n- **Consignes Claires** : Écrivez les consignes en phrases simples. Lisez-les à voix haute pour assurer la compréhension.\n- **Exercices Courts** : Proposez des exercices courts avec des réponses à choix multiples ou des questions à reponses courtes pour limiter la charge de lecture.\n\n**5. Utilisation de la Technologie**\n\n- **Ordinateurs et Tablettes** : Encouragez l'utilisation d'ordinateurs avec des logiciels d'aide à la lecture et à l'écriture.\n- **Outils de Lecture** : Fournissez des fichiers numériques que les élèves peuvent agrandir ou lire avec des dispositifs d'assistance vocale.\n\n**6. Temps et Évaluations**\n\n- **Temps Supplémentaire** : Accordez plus de temps pour les évaluations et les exercices.\n- **Corrections Immédiates** : Utilisez des outils qui permettent aux élèves de recevoir un retour immédiat sur leurs réponses.\n\nEn suivant ces recommandations, vous créerez un environnement d'apprentissage plus accessible et inclusif pour les élèves dyslexiques. Ces adaptations sont basées sur les recherches de Gasnier (2019), Meynaert (2022-2023) et Dias (2020) concernant les besoins spécifiques des élèves dyslexiques et les aménagements efficaces en classe.",
    "sources": [
      {
        "source": "LeMans_GASNIER_Amandine_EPD_2019.pdf",
        "author": "Amandine Gasnier",
        "section": "Content",
        "page": 17.0,
        "relevance_score": 0.512923539
      },
      {
        "source": "MEMOIRE Meynaert Emilie 2022-2023.pdf",
        "author": "Meynaert, E.",
        "section": "Content",
        "page": 23.0,
        "relevance_score": 0.508873522
      },
      {
        "source": "DIAS_Juliette_PE25_2020.pdf",
        "author": "Juliette Dias",
        "section": "Content",
        "page": 43.0,
        "relevance_score": 0.499863595
      },
      {
        "source": "DIAS_Juliette_PE25_2020.pdf",
        "author": "Juliette Dias",
        "section": "Content",
        "page": 42.0,
        "relevance_score": 0.497203916
      },
      {
        "source": "DIAS_Juliette_PE25_2020.pdf",
        "author": "Juliette Dias",
        "section": "SOMMAIRE",
        "page": 4.0,
        "relevance_score": 0.497083
      }
    ]
  },
  "assessment_adaptations": {
    "example_assessment": "# Évaluation adaptée pour le cours \"Civilsetmilitaires1GM\"\n\n## Objectif\nÉvaluer la compréhension des élèves sur les rôles des civils et des militaires pendant la Première Guerre mondiale.\n\n## Consignes de l'exercice\n\n### Présentation\n- Utilisation de la police de caractères \"Open Dyslexic\".\n- Mise en page aérée avec des espaces entre chaque question.\n- Consignes lues à voix haute avant de commencer l'exercice.\n\n### Exercice\n\n1. **Vrai ou Faux :** \n   - Les civils ont participé à l'effort de guerre en travaillant dans les usines. \n     - [ ] Vrai \n     - [ ] Faux\n\n2. **Question à choix multiples :**\n   Quel était le rôle principal des militaires pendant la Première Guerre mondiale ?\n   - [ ] Travailler dans les champs\n   - [ ] Combattre sur le front\n   - [ ] Enseigner dans les écoles\n\n3. **Associer les images :**\n   Associe chaque image avec le bon titre. (Fournir des images simples et claires)\n   - Image A : Soldat en uniforme\n   - Image B : Usine avec des ouvriers\n   - Titres possibles : \"Militaire\", \"Civil\"\n\n4. **Question ouverte :**\n   Explique avec tes mots ce que faisaient les civils pendant la guerre.\n   - Réponse attendue : Les civils fabriquaient des armes, travaillaient dans les usines, et soutenaient les soldats.\n\n### Supports visuels\n- Inclure des images de soldats, d'usines, et de scènes de vie quotidienne durant la guerre.\n- Fournir des schémas simples montrant la différence entre le front et l'arrière.\n\n### Temps supplémentaire\n- Offrir 10 minutes supplémentaires pour compléter l'évaluation.\n\n### Vérification de la compréhension\n- Poser des questions orales pour s'assurer que les consignes sont bien comprises.\n\nCes adaptations visent à réduire les obstacles liés à la lecture et à la compréhension pour les élèves dyslexiques, tout en leur permettant de démontrer leurs connaissances sur le sujet étudié.",
    "sources": [
      {
        "source": "DIAS_Juliette_PE25_2020.pdf",
        "author": "Juliette Dias",
        "section": "Content",
        "page": 42.0,
        "relevance_score": 0.547843814
      },
      {
        "source": "DIAS_Juliette_PE25_2020.pdf",
        "author": "Juliette Dias",
        "section": "Content",
        "page": 43.0,
        "relevance_score": 0.535271168
      },
      {
        "source": "MEMOIRE Meynaert Emilie 2022-2023.pdf",
        "author": "Meynaert, E.",
        "section": "Content",
        "page": 39.0,
        "relevance_score": 0.532713115
      },
      {
        "source": "MEMOIRE Meynaert Emilie 2022-2023.pdf",
        "author": "Meynaert, E.",
        "section": "2. Outils",
        "page": 35.0,
        "relevance_score": 0.531962454
      },
      {
        "source": "MEMOIRE Meynaert Emilie 2022-2023.pdf",
        "author": "Meynaert, E.",
        "section": "Content",
        "page": 23.0,
        "relevance_score": 0.520547032
      }
    ]
  },
  "generated_at": "2025-06-09T00:52:01.152786"
}